pycounts_cmwiebe24/__init__.py
pycounts_cmwiebe24/plotting.py
pycounts_cmwiebe24/pycounts_cmwiebe24.py
pycounts_cmwiebe24-0.1.0.dist-info/METADATA
pycounts_cmwiebe24-0.1.0.dist-info/WHEEL
pycounts_cmwiebe24-0.1.0.dist-info/RECORD
