Metadata-Version: 2.1
Name: pycounts_cmwiebe24
Version: 0.1.0
Summary: This is a simple package I am developing to teach myself about python package development.
License: None
Author: Caleb Wiebe
Requires-Python: >=3.9
Classifier: License :: Other/Proprietary License
Classifier: Programming Language :: Python :: 3
Classifier: Programming Language :: Python :: 3.9
Classifier: Programming Language :: Python :: 3.10
Classifier: Programming Language :: Python :: 3.11
Classifier: Programming Language :: Python :: 3.12
Classifier: Programming Language :: Python :: 3.13
Requires-Dist: matplotlib (>=3.9.3)
